Metadata-Version: 1.2
Name: amplimap
Version: 0.4.20
Summary: amplicon/smMIP mapping and analysis pipeline
Home-page: https://github.com/koelling/amplimap/
Author: Nils Koelling
Author-email: git@nk.gl
License: Apache License, Version 2.0
Download-URL: https://github.com/koelling/amplimap/archive/v0.4.20.tar.gz
Keywords: amplimap amplicon smmip mapping analysis pipeline
Platform: any
Classifier: Development Status :: 4 - Beta
Classifier: License :: OSI Approved :: Apache Software License
Classifier: Operating System :: MacOS
Classifier: Operating System :: Unix
Classifier: Programming Language :: Python :: 3
Requires-Python: >=3
